kangforecast/__init__.py
kangforecast/add_db_FamilyIncome_FamilyProportion.py
kangforecast/cal_food.py
kangforecast/creat_sql_festivals_food.py
kangforecast/data_analysis.py
kangforecast/data_loader.py
kangforecast/incert_data_sql.py
kangforecast/kangfn.py
kangforecast/m1load.py
kangforecast/m2process.py
kangforecast/m3show.py
kangforecast/main.py
kangforecast/module1.py
kangforecast/plot_db.py
kangforecast/show_db.py
kangforecast/touch_db.py
kangforecast/touch_festivals_foold.py
tests/__init__.py
tests/check_kanglib.py
tests/test_analysis.py
tests/test_kangforecast.py
tests/test_m1m2m3.py
tests/test_module1.py
tests/test_pytest_m1m2m3.py
kangforecast-0.58.dist-info/METADATA
kangforecast-0.58.dist-info/WHEEL
kangforecast-0.58.dist-info/entry_points.txt
kangforecast-0.58.dist-info/top_level.txt
kangforecast-0.58.dist-info/RECORD
