Metadata-Version: 2.1
Name: kangforecast
Version: 0.58
Summary: A simple forecast package.
Home-page: https://www.linkedin.com/in/xiaowenkang/
Author: Xiaowen Kang
Author-email: kangxiaowen@gmail.com
Classifier: Development Status :: 3 - Alpha
Classifier: Intended Audience :: Developers
Classifier: License :: OSI Approved :: MIT License
Classifier: Programming Language :: Python :: 3
Classifier: Programming Language :: Python :: 3.6
Classifier: Programming Language :: Python :: 3.7
Classifier: Programming Language :: Python :: 3.8
Classifier: Programming Language :: Python :: 3.9
Requires-Dist: kanglib
Requires-Dist: pandas
